{
  "info": {
    "_postman_id": "db40f015-ebaa-4699-b7e6-cc27daff5ee3",
    "name": "Products",
    "schema": "https://schema.getpostman.com/json/collection/v2.1.0/collection.json",
    "_exporter_id": "36307325"
  },
  "item": [
    {
      "name": "Add Product - Admin",
      "request": {
        "method": "POST",
        "header": [],
        "body": {
          "mode": "raw",
          "raw": "{\r\n    \"productName\": \"Nike Full Force\",\r\n    \"image\": \"default.png\",\r\n    \"description\": \"Sneakers\",\r\n    \"quantity\": 10,\r\n    \"price\": 500.0,\r\n    \"discount\": 10.0,\r\n    \"specialPrice\": 4500.0\r\n}",
          "options": {
            "raw": {
              "language": "json"
            }
          }
        },
        "url": {
          "raw": "http://localhost:8080/api/admin/categories/1/product",
          "protocol": "http",
          "host": [
            "localhost"
          ],
          "port": "8080",
          "path": [
            "api",
            "admin",
            "categories",
            "1",
            "product"
          ]
        }
      },
      "response": []
    },
    {
      "name": "Get All Products",
      "protocolProfileBehavior": {
        "disableBodyPruning": true
      },
      "request": {
        "method": "GET",
        "header": [],
        "body": {
          "mode": "raw",
          "raw": "{\r\n    \"categoryName\": \"FOR DELETION\"\r\n}"
        },
        "url": {
          "raw": "http://localhost:8080/api/public/products",
          "protocol": "http",
          "host": [
            "localhost"
          ],
          "port": "8080",
          "path": [
            "api",
            "public",
            "products"
          ]
        }
      },
      "response": []
    },
    {
      "name": "Get Products By Category",
      "request": {
        "method": "GET",
        "header": [],
        "url": {
          "raw": "http://localhost:8080/api/public/categories/2/products",
          "protocol": "http",
          "host": [
            "localhost"
          ],
          "port": "8080",
          "path": [
            "api",
            "public",
            "categories",
            "2",
            "products"
          ]
        }
      },
      "response": []
    },
    {
      "name": "Get Products By Keyword",
      "request": {
        "method": "GET",
        "header": [],
        "url": {
          "raw": "http://localhost:8080/api/public/products/keyword/ful?pageNumber=0&pageSize=10&sortBy=productName&sortOrder=desc",
          "protocol": "http",
          "host": [
            "localhost"
          ],
          "port": "8080",
          "path": [
            "api",
            "public",
            "products",
            "keyword",
            "ful"
          ],
          "query": [
            {
              "key": "pageNumber",
              "value": "0"
            },
            {
              "key": "pageSize",
              "value": "10"
            },
            {
              "key": "sortBy",
              "value": "productName"
            },
            {
              "key": "sortOrder",
              "value": "desc"
            }
          ]
        }
      },
      "response": []
    },
    {
      "name": "Update Product",
      "request": {
        "method": "PUT",
        "header": [],
        "body": {
          "mode": "raw",
          "raw": "{\r\n    \"productId\": 4,\r\n    \"productName\": \"Nike Air Force\",\r\n    \"image\": \"default.png\",\r\n    \"description\": \"Sneakers\",\r\n    \"quantity\": 10,\r\n    \"price\": 500.0,\r\n    \"discount\": 10.0,\r\n    \"specialPrice\": 4500.0\r\n}",
          "options": {
            "raw": {
              "language": "json"
            }
          }
        },
        "url": {
          "raw": "http://localhost:8080/api/admin/products/4",
          "protocol": "http",
          "host": [
            "localhost"
          ],
          "port": "8080",
          "path": [
            "api",
            "admin",
            "products",
            "4"
          ]
        }
      },
      "response": []
    },
    {
      "name": "Delete Product",
      "request": {
        "method": "DELETE",
        "header": [],
        "url": {
          "raw": "http://localhost:8080/api/admin/products/3",
          "protocol": "http",
          "host": [
            "localhost"
          ],
          "port": "8080",
          "path": [
            "api",
            "admin",
            "products",
            "3"
          ]
        }
      },
      "response": []
    },
    {
      "name": "Update Product Image",
      "request": {
        "method": "PUT",
        "header": [],
        "body": {
          "mode": "formdata",
          "formdata": [
            {
              "key": "image",
              "type": "file",
              "uuid": "60dc3837-fac6-4d2e-821c-604be57aa2c6",
              "src": "/C:/Users/john.valencia/Downloads/nike.jpg"
            }
          ]
        },
        "url": {
          "raw": "http://localhost:8080/api/products/4/image",
          "protocol": "http",
          "host": [
            "localhost"
          ],
          "port": "8080",
          "path": [
            "api",
            "products",
            "4",
            "image"
          ]
        }
      },
      "response": []
    }
  ]
}